polygon_access/__init__.py
polygon_access/access_nn2094.py
polygon_api_access_nn2094-0.1.0.dist-info/METADATA
polygon_api_access_nn2094-0.1.0.dist-info/WHEEL
polygon_api_access_nn2094-0.1.0.dist-info/top_level.txt
polygon_api_access_nn2094-0.1.0.dist-info/RECORD
