Metadata-Version: 2.1
Name: polygon-api-access-nn2094
Version: 0.1.0
Summary: Library for Homework
Home-page: https://polygon-api-access-nn2094.readthedocs.io/
Author: Nilansh Netan
Author-email: nn2094@nyu.edu
License: MIT
Platform: UNKNOWN
Classifier: Intended Audience :: Developers
Classifier: License :: OSI Approved :: MIT License
Classifier: Programming Language :: Python
Classifier: Programming Language :: Python :: 3
Classifier: Programming Language :: Python :: 3.6
Classifier: Programming Language :: Python :: 3.7
Classifier: Programming Language :: Python :: 3.8
Classifier: Programming Language :: Python :: 3.9
Classifier: Operating System :: OS Independent
Requires-Dist: polygon-api-client
Requires-Dist: SQLAlchemy
